{
	"$schema": "https://schema.management.azure.com/schemas/2015-01-01/deploymentParameters.json#",
	"contentVersion": "1.0.0.0",
	"parameters": {
		"factoryName": {
			"value": "adfspotifyproject96"
		},
		"AzureDataLakeStorage_accountKey": {
			"value": ""
		},
		"AzureSql_password": {
			"value": ""
		},
		"AzureDataLakeStorage_properties_typeProperties_url": {
			"value": "https://spotify1996.dfs.core.windows.net/"
		},
		"AzureSql_properties_typeProperties_server": {
			"value": "chakriserver.database.windows.net"
		},
		"AzureSql_properties_typeProperties_database": {
			"value": "spotifydb96"
		},
		"AzureSql_properties_typeProperties_userName": {
			"value": "spotify96"
		},
		"containerUri": {
			"value": ""
		},
		"containerSasToken": {
			"value": ""
		}
	}
}